Workbook
Name ElectrolyzerCapacityMW: 'Assumptions'!$B$4
Name EfficiencykWhPerKg: 'Assumptions'!$B$5
Name CapacityFactor: 'Assumptions'!$B$6
Name DegradationRate: 'Assumptions'!$B$7
Name OfftakePrice: 'Assumptions'!$B$10
Name FixedOpexAnnual: 'Assumptions'!$B$11
Name VariableOpexPerKg: 'Assumptions'!$B$12
Name PowerPrice: 'Assumptions'!$B$13
Name WaterCostPerKg: 'Assumptions'!$B$14
Name StackReplacementCost: 'Assumptions'!$B$15
Name StackReplacementIntervalYrs: 'Assumptions'!$B$16
Name TotalCapex: 'Assumptions'!$B$19
Name ConstructionGearingPct: 'Assumptions'!$B$20
Name WACC: 'Assumptions'!$B$23
Name CostOfDebtRate: 'Assumptions'!$B$24
Name IDC_CashFundedPct_f: 'Assumptions'!$B$25
Name IDCTimingConvention: 'Assumptions'!$B$26
Name TargetDSCR_Input: 'Assumptions'!$B$27
Name MaxGearingPct: 'Assumptions'!$B$28
Name DebtTenorYears: 'Assumptions'!$B$29
Name ConstructionYears: 'Assumptions'!$B$30
Name OperationsYears: 'Assumptions'!$B$31
Name TenorEndPeriod: 'Control'!$B$1
Name CODPeriod: 'Control'!$C$1
Name Period_Row: 'Control'!$D$3:$CM$3
Name ConstructionFlag_Row: 'Control'!$D$6:$CM$6
Name OperationsFlag_Row: 'Control'!$D$7:$CM$7
Name DiscountFactor_Row: 'Control'!$D$12:$CM$12
Name YearsSinceCOD_Row: 'Control'!$D$9:$CM$9
Name QuarterInYear_Row: 'Control'!$D$5:$CM$5
Name CapexDraw_Row: 'Capex_Construction'!$D$3:$CM$3
Name EquityDrawCapex_Row: 'Capex_Construction'!$D$5:$CM$5
Name CashFundedInterest_Row: 'Capex_Construction'!$D$8:$CM$8
Name ClosingBalanceAtCOD: 'Capex_Construction'!$K$10
Name H2Production_Row: 'Ops_CFADS'!$D$3:$CM$3
Name CFADS_Row: 'Ops_CFADS'!$D$11:$CM$11
Name Interest_Row: 'Debt_Sizing_DSCR'!$D$5:$CM$5
Name Principal_Row: 'Debt_Sizing_DSCR'!$D$7:$CM$7
Name DSCR_Actual_Row: 'Debt_Sizing_DSCR'!$D$8:$CM$8
Name ClosingBalance_Debt_Row: 'Debt_Sizing_DSCR'!$D$9:$CM$9
Name EndingBalanceResidual: 'Debt_Sizing_DSCR'!$BS$9
Name GearingFactor: 'VBA_Control'!$B$3
Name Tolerance: 'VBA_Control'!$B$4
Name MaxIterations: 'VBA_Control'!$B$5
Name SizingMethod: 'VBA_Control'!$B$6
Name ConvergenceStatus: 'VBA_Control'!$B$7
Name IterationsUsed: 'VBA_Control'!$B$8
Name LCOH_CostNPV: 'LCOH'!$B$12
Name LCOH_VolumeNPV: 'LCOH'!$C$12
Name LCOH_USD_per_kg: 'LCOH'!$B$14
Name EquityCashFlow_Row: 'Returns_Sensitivities'!$D$3:$CM$3
Name EquityIRR: 'Returns_Sensitivities'!$B$6
Name SensitivityGrid_FirstRow: 'Returns_Sensitivities'!$A$14
Name SensitivityGrid_LastRow: 'Returns_Sensitivities'!$A$22

Sheet Cover
A1: Green Hydrogen LCOH Project-Finance Model
A3: Conventions:
A4: - Blue fill = hardcoded input. White = formula. Green fill = cross-sheet link.
A5: - Quarterly periods across columns D onward, one row per line item.
A6: - Construction: 2 yrs (8 quarters, periods 1-8).
A7: - Operations: 20 yrs (80 quarters, periods 9-88). COD = start of period 9.
A8: - Iterative calculation is deliberately kept OFF (File > Options > Formulas).
A9: Nothing in this model should ever need it -- if you see a circular-reference
A10: warning, that flags a real bug, not something to toggle a setting around.
A12: Circularity handling:
A13: - IDC (Interest During Construction) is solved in CLOSED FORM as a plain Excel
A14: formula on Capex_Construction (see the derivation there) -- no VBA, no
... A29: financeability check and does not feed the LCOH numerator.

Sheet Assumptions
A1: ASSUMPTIONS
A3: Technical
A4: Electrolyzer Capacity | B4: 100 | C4: MW
A5: Electrolyzer Efficiency | B5: 55 | C5: kWh/kg H2
A6: Capacity Factor | B6: 0.9 | C6: %
A7: Degradation Rate | B7: 0.005 | C7: %/yr
A9: Commercial
A10: H2 Offtake Price | B10: 4.5 | C10: $/kg
A11: Fixed Opex | B11: 5000000 | C11: $/yr
A12: Variable Opex | B12: 0.2 | C12: $/kg
A13: Power Price | B13: 40 | C13: $/MWh
A14: Water Cost | B14: 0.05 | C14: $/kg
A15: Stack Replacement Cost | B15: 20000000 | C15: $
A16: Stack Replacement Interval | B16: 8 | C16: yrs
A18: Capex
A19: Total Capex | B19: 400000000 | C19: $
A20: Construction Debt-Funded % | B20: 0.7 | C20: % | E20: Share of capex draws funded by debt during construction (rest is equity)
A22: Financing
A23: WACC | B23: 0.08 | C23: %
A24: Cost of Debt | B24: 0.06 | C24: %
A25: IDC Cash-Funded Fraction (f) | B25: 0.3 | C25: % | E25: 0 = fully capitalized, 1 = fully cash-funded by equity/reserve
A26: IDC Timing Convention | B26: MidPeriod | E26: MidPeriod (closed-form algebra) or EndPeriod (simple, already non-circular)
A27: Target DSCR | B27: 1.35 | C27: x
A28: Max Gearing | B28: 0.8 | C28: %
A29: Debt Tenor | B29: 15 | C29: yrs
A30: Construction Period | B30: 2 | C30: yrs
A31: Operations Period | B31: 20 | C31: yrs

Sheet Control
A1: CONTROL / MASTER TIMELINE | B1: =ConstructionYears*4+DebtTenorYears*4 | C1: =ConstructionYears*4+1
A3: Period # | D3: 1 | E3: 2 | F3: 3 | G3: 4 | H3: 5 | I3: 6 | J3: 7 | K3: 8 | L3: 9 | M3: 10 | N3: 11 | O3: 12 | P3: 13 | Q3: 14 | R3: 15 | S3: 16 | T3: 17 | U3: 18 | V3: 19 | W3: 20 | X3: 21 | Y3: 22 | Z3: 23 | AA3: 24 | AB3: 25 | AC3: 26 | AD3: 27 | AE3: 28 | AF3: 29 | AG3: 30 | AH3: 31 | AI3: 32 | AJ3: 33 | AK3: 34 | AL3: 35 | AM3: 36 | AN3: 37 | AO3: 38 | AP3: 39 | AQ3: 40 | AR3: 41 | AS3: 42 | AT3: 43 | AU3: 44 | AV3: 45 | AW3: 46 | AX3: 47 | AY3: 48 | AZ3: 49 | BA3: 50 | BB3: 51 | BC3: 52 | BD3: 53 | BE3: 54 | BF3: 55 | BG3: 56 | BH3: 57 | BI3: 58 | BJ3: 59 | BK3: 60 | BL3: 61 | BM3: 62 | BN3: 63 | BO3: 64 | BP3: 65 | BQ3: 66 | BR3: 67 | BS3: 68 | BT3: 69 | BU3: 70 | BV3: 71 | BW3: 72 | BX3: 73 | BY3: 74 | BZ3: 75 | CA3: 76 | CB3: 77 | CC3: 78 | CD3: 79 | CE3: 80 | CF3: 81 | CG3: 82 | CH3: 83 | CI3: 84 | CJ3: 85 | CK3: 86 | CL3: 87 | CM3: 88
A4: Year # | D4: =ROUNDUP(D3/4,0) | E4: =ROUNDUP(E3/4,0) | F4: =ROUNDUP(F3/4,0) | G4: =ROUNDUP(G3/4,0) | H4: =ROUNDUP(H3/4,0) | I4: =ROUNDUP(I3/4,0) | J4: =ROUNDUP(J3/4,0) | K4: =ROUNDUP(K3/4,0) | ... CM4: =ROUNDUP(CM3/4,0)
A5: Quarter in Year | D5: =D3-(D4-1)*4 | E5: =E3-(E4-1)*4 | F5: =F3-(F4-1)*4 | G5: =G3-(G4-1)*4 | H5: =H3-(H4-1)*4 | I5: =I3-(I4-1)*4 | J5: =J3-(J4-1)*4 | K5: =K3-(K4-1)*4 | ... CM5: =CM3-(CM4-1)*4
A6: Construction Flag | D6: =IF(D3<=ConstructionYears*4,1,0) | E6: =IF(E3<=ConstructionYears*4,1,0) | F6: =IF(F3<=ConstructionYears*4,1,0) | G6: =IF(G3<=ConstructionYears*4,1,0) | H6: =IF(H3<=ConstructionYears*4,1,0) | I6: =IF(I3<=ConstructionYears*4,1,0) | J6: =IF(J3<=ConstructionYears*4,1,0) | K6: =IF(K3<=ConstructionYears*4,1,0) | ... CM6: =IF(CM3<=ConstructionYears*4,1,0)
A7: Operations Flag | D7: =IF(D3>ConstructionYears*4,1,0) | E7: =IF(E3>ConstructionYears*4,1,0) | F7: =IF(F3>ConstructionYears*4,1,0) | G7: =IF(G3>ConstructionYears*4,1,0) | H7: =IF(H3>ConstructionYears*4,1,0) | I7: =IF(I3>ConstructionYears*4,1,0) | J7: =IF(J3>ConstructionYears*4,1,0) | K7: =IF(K3>ConstructionYears*4,1,0) | ... CM7: =IF(CM3>ConstructionYears*4,1,0)
A8: COD Flag | D8: =IF(D3=ConstructionYears*4+1,1,0) | E8: =IF(E3=ConstructionYears*4+1,1,0) | F8: =IF(F3=ConstructionYears*4+1,1,0) | G8: =IF(G3=ConstructionYears*4+1,1,0) | H8: =IF(H3=ConstructionYears*4+1,1,0) | I8: =IF(I3=ConstructionYears*4+1,1,0) | J8: =IF(J3=ConstructionYears*4+1,1,0) | K8: =IF(K3=ConstructionYears*4+1,1,0) | ... CM8: =IF(CM3=ConstructionYears*4+1,1,0)
A9: Years Since COD | D9: =D4-ConstructionYears | E9: =E4-ConstructionYears | F9: =F4-ConstructionYears | G9: =G4-ConstructionYears | H9: =H4-ConstructionYears | I9: =I4-ConstructionYears | J9: =J4-ConstructionYears | K9: =K4-ConstructionYears | ... CM9: =CM4-ConstructionYears
A10: Periodic Debt Rate | D10: =(1+CostOfDebtRate)^0.25-1 | E10: =(1+CostOfDebtRate)^0.25-1 | F10: =(1+CostOfDebtRate)^0.25-1 | G10: =(1+CostOfDebtRate)^0.25-1 | H10: =(1+CostOfDebtRate)^0.25-1 | I10: =(1+CostOfDebtRate)^0.25-1 | J10: =(1+CostOfDebtRate)^0.25-1 | K10: =(1+CostOfDebtRate)^0.25-1 | ... CM10: =(1+CostOfDebtRate)^0.25-1
A11: Periodic WACC | D11: =(1+WACC)^0.25-1 | E11: =(1+WACC)^0.25-1 | F11: =(1+WACC)^0.25-1 | G11: =(1+WACC)^0.25-1 | H11: =(1+WACC)^0.25-1 | I11: =(1+WACC)^0.25-1 | J11: =(1+WACC)^0.25-1 | K11: =(1+WACC)^0.25-1 | ... CM11: =(1+WACC)^0.25-1
A12: Cumulative Discount Factor (WACC) | D12: =1/(1+D11)^D3 | E12: =1/(1+E11)^E3 | F12: =1/(1+F11)^F3 | G12: =1/(1+G11)^G3 | H12: =1/(1+H11)^H3 | I12: =1/(1+I11)^I3 | J12: =1/(1+J11)^J3 | K12: =1/(1+K11)^K3 | ... CM12: =1/(1+CM11)^CM3

Sheet Capex_Construction
A1: CAPEX & CONSTRUCTION DRAWDOWN
A3: Capex Draw (Total) | C3: $ | D3: =IF(Control!D6=1,TotalCapex/(ConstructionYears*4),0) | E3: =IF(Control!E6=1,TotalCapex/(ConstructionYears*4),0) | F3: =IF(Control!F6=1,TotalCapex/(ConstructionYears*4),0) | G3: =IF(Control!G6=1,TotalCapex/(ConstructionYears*4),0) | H3: =IF(Control!H6=1,TotalCapex/(ConstructionYears*4),0) | I3: =IF(Control!I6=1,TotalCapex/(ConstructionYears*4),0) | J3: =IF(Control!J6=1,TotalCapex/(ConstructionYears*4),0) | K3: =IF(Control!K6=1,TotalCapex/(ConstructionYears*4),0) | ... CM3: =IF(Control!CM6=1,TotalCapex/(ConstructionYears*4),0)
A4: Debt Draw for Capex (D_t) | C4: $ | D4: =D3*ConstructionGearingPct | E4: =E3*ConstructionGearingPct | F4: =F3*ConstructionGearingPct | G4: =G3*ConstructionGearingPct | H4: =H3*ConstructionGearingPct | I4: =I3*ConstructionGearingPct | J4: =J3*ConstructionGearingPct | K4: =K3*ConstructionGearingPct | ... CM4: =CM3*ConstructionGearingPct
A5: Equity Draw for Capex | C5: $ | D5: =D3*(1-ConstructionGearingPct) | E5: =E3*(1-ConstructionGearingPct) | F5: =F3*(1-ConstructionGearingPct) | G5: =G3*(1-ConstructionGearingPct) | H5: =H3*(1-ConstructionGearingPct) | I5: =I3*(1-ConstructionGearingPct) | J5: =J3*(1-ConstructionGearingPct) | K5: =K3*(1-ConstructionGearingPct) | ... CM5: =CM3*(1-ConstructionGearingPct)
A6: Opening Debt Balance (B_t-1) | C6: $ | D6: 0 | E6: =D10 | F6: =E10 | G6: =F10 | H6: =G10 | I6: =H10 | J6: =I10 | K6: =J10 | L6: =K10 | ... CM6: =CL10
A7: Interest I_t (closed form) | C7: $ | D7: =IF(IDCTimingConvention="EndPeriod",Control!D10*(D6+D4),(Control!D10*(D6+D4/2))/(1-Control!D10*(1-IDC_CashFundedPct_f)/2)) | E7: =IF(IDCTimingConvention="EndPeriod",Control!E10*(E6+E4),(Control!E10*(E6+E4/2))/(1-Control!E10*(1-IDC_CashFundedPct_f)/2)) | F7: =IF(IDCTimingConvention="EndPeriod",Control!F10*(F6+F4),(Control!F10*(F6+F4/2))/(1-Control!F10*(1-IDC_CashFundedPct_f)/2)) | G7: =IF(IDCTimingConvention="EndPeriod",Control!G10*(G6+G4),(Control!G10*(G6+G4/2))/(1-Control!G10*(1-IDC_CashFundedPct_f)/2)) | H7: =IF(IDCTimingConvention="EndPeriod",Control!H10*(H6+H4),(Control!H10*(H6+H4/2))/(1-Control!H10*(1-IDC_CashFundedPct_f)/2)) | I7: =IF(IDCTimingConvention="EndPeriod",Control!I10*(I6+I4),(Control!I10*(I6+I4/2))/(1-Control!I10*(1-IDC_CashFundedPct_f)/2)) | J7: =IF(IDCTimingConvention="EndPeriod",Control!J10*(J6+J4),(Control!J10*(J6+J4/2))/(1-Control!J10*(1-IDC_CashFundedPct_f)/2)) | K7: =IF(IDCTimingConvention="EndPeriod",Control!K10*(K6+K4),(Control!K10*(K6+K4/2))/(1-Control!K10*(1-IDC_CashFundedPct_f)/2)) | ... CM7: =IF(IDCTimingConvention="EndPeriod",Control!CM10*(CM6+CM4),(Control!CM10*(CM6+CM4/2))/(1-Control!CM10*(1-IDC_CashFundedPct_f)/2))
A8: Cash-Funded Interest (f x I_t) | C8: $ | D8: =IDC_CashFundedPct_f*D7 | E8: =IDC_CashFundedPct_f*E7 | F8: =IDC_CashFundedPct_f*F7 | G8: =IDC_CashFundedPct_f*G7 | H8: =IDC_CashFundedPct_f*H7 | I8: =IDC_CashFundedPct_f*I7 | J8: =IDC_CashFundedPct_f*J7 | K8: =IDC_CashFundedPct_f*K7 | ... CM8: =IDC_CashFundedPct_f*CM7
A9: Capitalized Interest ((1-f) x I_t) | C9: $ | D9: =(1-IDC_CashFundedPct_f)*D7 | E9: =(1-IDC_CashFundedPct_f)*E7 | F9: =(1-IDC_CashFundedPct_f)*F7 | G9: =(1-IDC_CashFundedPct_f)*G7 | H9: =(1-IDC_CashFundedPct_f)*H7 | I9: =(1-IDC_CashFundedPct_f)*I7 | J9: =(1-IDC_CashFundedPct_f)*J7 | K9: =(1-IDC_CashFundedPct_f)*K7 | ... CM9: =(1-IDC_CashFundedPct_f)*CM7
A10: Closing Debt Balance (B_t) | C10: $ | D10: =D6+D4+D9 | E10: =E6+E4+E9 | F10: =F6+F4+F9 | G10: =G6+G4+G9 | H10: =H6+H4+H9 | I10: =I6+I4+I9 | J10: =J6+J4+J9 | K10: =K6+K4+K9 | ... CM10: =CM6+CM4+CM9
A13: I_t = r*(B_(t-1) + D_t/2) / (1 - r*(1-f)/2) [mid-period, algebraically isolated -- not circular]
A14: I_t = r*(B_(t-1) + D_t) [end-of-period draw convention, no algebra needed]

Sheet Ops_CFADS
A1: OPERATIONS & CFADS
A3: H2 Production | C3: kg | D3: =Control!D7*ElectrolyzerCapacityMW*1000*2191.5*CapacityFactor/EfficiencykWhPerKg*(1-DegradationRate)^MAX(Control!D9-1,0) | E3: =Control!E7*ElectrolyzerCapacityMW*1000*2191.5*CapacityFactor/EfficiencykWhPerKg*(1-DegradationRate)^MAX(Control!E9-1,0) | F3: =Control!F7*ElectrolyzerCapacityMW*1000*2191.5*CapacityFactor/EfficiencykWhPerKg*(1-DegradationRate)^MAX(Control!F9-1,0) | G3: =Control!G7*ElectrolyzerCapacityMW*1000*2191.5*CapacityFactor/EfficiencykWhPerKg*(1-DegradationRate)^MAX(Control!G9-1,0) | H3: =Control!H7*ElectrolyzerCapacityMW*1000*2191.5*CapacityFactor/EfficiencykWhPerKg*(1-DegradationRate)^MAX(Control!H9-1,0) | I3: =Control!I7*ElectrolyzerCapacityMW*1000*2191.5*CapacityFactor/EfficiencykWhPerKg*(1-DegradationRate)^MAX(Control!I9-1,0) | J3: =Control!J7*ElectrolyzerCapacityMW*1000*2191.5*CapacityFactor/EfficiencykWhPerKg*(1-DegradationRate)^MAX(Control!J9-1,0) | K3: =Control!K7*ElectrolyzerCapacityMW*1000*2191.5*CapacityFactor/EfficiencykWhPerKg*(1-DegradationRate)^MAX(Control!K9-1,0) | ... CM3: =Control!CM7*ElectrolyzerCapacityMW*1000*2191.5*CapacityFactor/EfficiencykWhPerKg*(1-DegradationRate)^MAX(Control!CM9-1,0)
A4: Revenue | C4: $ | D4: =D3*OfftakePrice | E4: =E3*OfftakePrice | F4: =F3*OfftakePrice | G4: =G3*OfftakePrice | H4: =H3*OfftakePrice | I4: =I3*OfftakePrice | J4: =J3*OfftakePrice | K4: =K3*OfftakePrice | ... CM4: =CM3*OfftakePrice
A5: Fixed Opex | C5: $ | D5: =Control!D7*FixedOpexAnnual/4 | E5: =Control!E7*FixedOpexAnnual/4 | F5: =Control!F7*FixedOpexAnnual/4 | G5: =Control!G7*FixedOpexAnnual/4 | H5: =Control!H7*FixedOpexAnnual/4 | I5: =Control!I7*FixedOpexAnnual/4 | J5: =Control!J7*FixedOpexAnnual/4 | K5: =Control!K7*FixedOpexAnnual/4 | ... CM5: =Control!CM7*FixedOpexAnnual/4
A6: Variable Opex | C6: $ | D6: =D3*VariableOpexPerKg | E6: =E3*VariableOpexPerKg | F6: =F3*VariableOpexPerKg | G6: =G3*VariableOpexPerKg | H6: =H3*VariableOpexPerKg | I6: =I3*VariableOpexPerKg | J6: =J3*VariableOpexPerKg | K6: =K3*VariableOpexPerKg | ... CM6: =CM3*VariableOpexPerKg
A7: Power Cost | C7: $ | D7: =D3*EfficiencykWhPerKg/1000*PowerPrice | E7: =E3*EfficiencykWhPerKg/1000*PowerPrice | F7: =F3*EfficiencykWhPerKg/1000*PowerPrice | G7: =G3*EfficiencykWhPerKg/1000*PowerPrice | H7: =H3*EfficiencykWhPerKg/1000*PowerPrice | I7: =I3*EfficiencykWhPerKg/1000*PowerPrice | J7: =J3*EfficiencykWhPerKg/1000*PowerPrice | K7: =K3*EfficiencykWhPerKg/1000*PowerPrice | ... CM7: =CM3*EfficiencykWhPerKg/1000*PowerPrice
A8: Water Cost | C8: $ | D8: =D3*WaterCostPerKg | E8: =E3*WaterCostPerKg | F8: =F3*WaterCostPerKg | G8: =G3*WaterCostPerKg | H8: =H3*WaterCostPerKg | I8: =I3*WaterCostPerKg | J8: =J3*WaterCostPerKg | K8: =K3*WaterCostPerKg | ... CM8: =CM3*WaterCostPerKg
A9: Stack Replacement Capex | C9: $ | D9: =IF(AND(Control!D7=1,Control!D9>0,MOD(Control!D9,StackReplacementIntervalYrs)=0,Control!D5=4),StackReplacementCost,0) | E9: =IF(AND(Control!E7=1,Control!E9>0,MOD(Control!E9,StackReplacementIntervalYrs)=0,Control!E5=4),StackReplacementCost,0) | F9: =IF(AND(Control!F7=1,Control!F9>0,MOD(Control!F9,StackReplacementIntervalYrs)=0,Control!F5=4),StackReplacementCost,0) | G9: =IF(AND(Control!G7=1,Control!G9>0,MOD(Control!G9,StackReplacementIntervalYrs)=0,Control!G5=4),StackReplacementCost,0) | H9: =IF(AND(Control!H7=1,Control!H9>0,MOD(Control!H9,StackReplacementIntervalYrs)=0,Control!H5=4),StackReplacementCost,0) | I9: =IF(AND(Control!I7=1,Control!I9>0,MOD(Control!I9,StackReplacementIntervalYrs)=0,Control!I5=4),StackReplacementCost,0) | J9: =IF(AND(Control!J7=1,Control!J9>0,MOD(Control!J9,StackReplacementIntervalYrs)=0,Control!J5=4),StackReplacementCost,0) | K9: =IF(AND(Control!K7=1,Control!K9>0,MOD(Control!K9,StackReplacementIntervalYrs)=0,Control!K5=4),StackReplacementCost,0) | ... CM9: =IF(AND(Control!CM7=1,Control!CM9>0,MOD(Control!CM9,StackReplacementIntervalYrs)=0,Control!CM5=4),StackReplacementCost,0)
A10: EBITDA | C10: $ | D10: =D4-D5-D6-D7-D8 | E10: =E4-E5-E6-E7-E8 | F10: =F4-F5-F6-F7-F8 | G10: =G4-G5-G6-G7-G8 | H10: =H4-H5-H6-H7-H8 | I10: =I4-I5-I6-I7-I8 | J10: =J4-J5-J6-J7-J8 | K10: =K4-K5-K6-K7-K8 | ... CM10: =CM4-CM5-CM6-CM7-CM8
A11: CFADS | C11: $ | D11: =D10-D9 | E11: =E10-E9 | F11: =F10-F9 | G11: =G10-G9 | H11: =H10-H9 | I11: =I10-I9 | J11: =J10-J9 | K11: =K10-K9 | ... CM11: =CM10-CM9

Sheet Debt_Sizing_DSCR
A1: DEBT SIZING & DSCR SCULPTING
A4: Opening Balance | C4: $ | D4: 0 | E4: 0 | F4: 0 | G4: 0 | H4: 0 | I4: 0 | J4: 0 | K4: 0 | L4: =ClosingBalanceAtCOD*GearingFactor | M4: =L9 | N4: =M9 | O4: =N9 | P4: =O9 | Q4: =P9 | R4: =Q9 | S4: =R9 | T4: =S9 | ... BS4: =BR9 | BT4: 0 | BU4: 0 | BV4: 0 | BW4: 0 | BX4: 0 | BY4: 0 | BZ4: 0 | CA4: 0 | CB4: 0 | CC4: 0 | CD4: 0 | CE4: 0 | CF4: 0 | CG4: 0 | CH4: 0 | CI4: 0 | CJ4: 0 | CK4: 0 | CL4: 0 | CM4: 0
A5: Interest_t = r x Opening | C5: $ | D5: =Control!D10*D4 | E5: =Control!E10*E4 | F5: =Control!F10*F4 | G5: =Control!G10*G4 | H5: =Control!H10*H4 | I5: =Control!I10*I4 | J5: =Control!J10*J4 | K5: =Control!K10*K4 | ... CM5: =Control!CM10*CM4
A6: CFADS (link) | C6: $ | D6: ='Ops_CFADS'!D11 | E6: ='Ops_CFADS'!E11 | F6: ='Ops_CFADS'!F11 | G6: ='Ops_CFADS'!G11 | H6: ='Ops_CFADS'!H11 | I6: ='Ops_CFADS'!I11 | J6: ='Ops_CFADS'!J11 | K6: ='Ops_CFADS'!K11 | ... CM6: ='Ops_CFADS'!CM11
A7: Principal_t (sculpted) | C7: $ | D7: 0 | E7: 0 | F7: 0 | G7: 0 | H7: 0 | I7: 0 | J7: 0 | K7: 0 | L7: =IF(L4=0,0,MIN(L4,MAX(0,L6/TargetDSCR_Input-L5))) | M7: =IF(M4=0,0,MIN(M4,MAX(0,M6/TargetDSCR_Input-M5))) | N7: =IF(N4=0,0,MIN(N4,MAX(0,N6/TargetDSCR_Input-N5))) | O7: =IF(O4=0,0,MIN(O4,MAX(0,O6/TargetDSCR_Input-O5))) | P7: =IF(P4=0,0,MIN(P4,MAX(0,P6/TargetDSCR_Input-P5))) | Q7: =IF(Q4=0,0,MIN(Q4,MAX(0,Q6/TargetDSCR_Input-Q5))) | R7: =IF(R4=0,0,MIN(R4,MAX(0,R6/TargetDSCR_Input-R5))) | S7: =IF(S4=0,0,MIN(S4,MAX(0,S6/TargetDSCR_Input-S5))) | ... BS7: =IF(BS4=0,0,MIN(BS4,MAX(0,BS6/TargetDSCR_Input-BS5))) | BT7: 0 | BU7: 0 | BV7: 0 | BW7: 0 | BX7: 0 | BY7: 0 | BZ7: 0 | CA7: 0 | CB7: 0 | CC7: 0 | CD7: 0 | CE7: 0 | CF7: 0 | CG7: 0 | CH7: 0 | CI7: 0 | CJ7: 0 | CK7: 0 | CL7: 0 | CM7: 0
A8: Actual DSCR | C8: x | L8: =IF((L5+L7)=0,"",L6/(L5+L7)) | M8: =IF((M5+M7)=0,"",M6/(M5+M7)) | N8: =IF((N5+N7)=0,"",N6/(N5+N7)) | O8: =IF((O5+O7)=0,"",O6/(O5+O7)) | P8: =IF((P5+P7)=0,"",P6/(P5+P7)) | Q8: =IF((Q5+Q7)=0,"",Q6/(Q5+Q7)) | R8: =IF((R5+R7)=0,"",R6/(R5+R7)) | S8: =IF((S5+S7)=0,"",S6/(S5+S7)) | ... BS8: =IF((BS5+BS7)=0,"",BS6/(BS5+BS7))
A9: Closing Balance | C9: $ | D9: =D4 | E9: =E4 | F9: =F4 | G9: =G4 | H9: =H4 | I9: =I4 | J9: =J4 | K9: =K4 | L9: =L4-L7 | M9: =M4-M7 | N9: =N4-N7 | O9: =O4-O7 | P9: =P4-P7 | Q9: =Q4-Q7 | R9: =R4-R7 | S9: =S4-S7 | ... BS9: =BS4-BS7 | BT9: =BT4 | BU9: =BU4 | BV9: =BV4 | BW9: =BW4 | BX9: =BX4 | BY9: =BY4 | BZ9: =BZ4 | CA9: =CA4 | ... CM9: =CM4

Sheet VBA_Control
A1: VBA CONTROL (bisection scalars)
A3: GearingFactor | B3: 1 | D3: Debt quantum multiplier on ClosingBalanceAtCOD -- VBA bisects this
A4: Tolerance | B4: 1000 | D4: $ tolerance on EndingBalanceResidual for convergence
A5: MaxIterations | B5: 100 | D5: Bisection iteration cap
A6: SizingMethod | B6: GearingQuantum | D6: GearingQuantum (recommended) or DSCRMultiple
A7: ConvergenceStatus | B7: Not run | D7: Written by RunDebtSizing
A8: IterationsUsed | B8: 0 | D8: Written by RunDebtSizing

Sheet Financials_3Statement
A1: FINANCIALS SUMMARY (unaudited, simplified)
A3: EBITDA | C3: $ | D3: ='Ops_CFADS'!D10 | E3: ='Ops_CFADS'!E10 | F3: ='Ops_CFADS'!F10 | G3: ='Ops_CFADS'!G10 | H3: ='Ops_CFADS'!H10 | I3: ='Ops_CFADS'!I10 | J3: ='Ops_CFADS'!J10 | K3: ='Ops_CFADS'!K10 | ... CM3: ='Ops_CFADS'!CM10
A4: Interest Expense | C4: $ | D4: ='Debt_Sizing_DSCR'!D5 | E4: ='Debt_Sizing_DSCR'!E5 | F4: ='Debt_Sizing_DSCR'!F5 | G4: ='Debt_Sizing_DSCR'!G5 | H4: ='Debt_Sizing_DSCR'!H5 | I4: ='Debt_Sizing_DSCR'!I5 | J4: ='Debt_Sizing_DSCR'!J5 | K4: ='Debt_Sizing_DSCR'!K5 | ... CM4: ='Debt_Sizing_DSCR'!CM5
A5: Principal Repayment | C5: $ | D5: ='Debt_Sizing_DSCR'!D7 | E5: ='Debt_Sizing_DSCR'!E7 | F5: ='Debt_Sizing_DSCR'!F7 | G5: ='Debt_Sizing_DSCR'!G7 | H5: ='Debt_Sizing_DSCR'!H7 | I5: ='Debt_Sizing_DSCR'!I7 | J5: ='Debt_Sizing_DSCR'!J7 | K5: ='Debt_Sizing_DSCR'!K7 | ... CM5: ='Debt_Sizing_DSCR'!CM7
A6: Net Cash Flow to Equity (post-debt) | C6: $ | D6: =D3-D4-D5 | E6: =E3-E4-E5 | F6: =F3-F4-F5 | G6: =G3-G4-G5 | H6: =H3-H4-H5 | I6: =I3-I4-I5 | J6: =J3-J4-J5 | K6: =K3-K4-K5 | ... CM6: =CM3-CM4-CM5

Sheet LCOH
A1: LCOH (UNLEVERED)
A3: Capex_t | C3: $ | D3: ='Capex_Construction'!D3 | E3: ='Capex_Construction'!E3 | F3: ='Capex_Construction'!F3 | G3: ='Capex_Construction'!G3 | H3: ='Capex_Construction'!H3 | I3: ='Capex_Construction'!I3 | J3: ='Capex_Construction'!J3 | K3: ='Capex_Construction'!K3 | ... CM3: ='Capex_Construction'!CM3
A4: Opex_t (fixed+var+power+water+stack) | C4: $ | D4: ='Ops_CFADS'!D5+'Ops_CFADS'!D6+'Ops_CFADS'!D7+'Ops_CFADS'!D8+'Ops_CFADS'!D9 | E4: ='Ops_CFADS'!E5+'Ops_CFADS'!E6+'Ops_CFADS'!E7+'Ops_CFADS'!E8+'Ops_CFADS'!E9 | F4: ='Ops_CFADS'!F5+'Ops_CFADS'!F6+'Ops_CFADS'!F7+'Ops_CFADS'!F8+'Ops_CFADS'!F9 | G4: ='Ops_CFADS'!G5+'Ops_CFADS'!G6+'Ops_CFADS'!G7+'Ops_CFADS'!G8+'Ops_CFADS'!G9 | H4: ='Ops_CFADS'!H5+'Ops_CFADS'!H6+'Ops_CFADS'!H7+'Ops_CFADS'!H8+'Ops_CFADS'!H9 | I4: ='Ops_CFADS'!I5+'Ops_CFADS'!I6+'Ops_CFADS'!I7+'Ops_CFADS'!I8+'Ops_CFADS'!I9 | J4: ='Ops_CFADS'!J5+'Ops_CFADS'!J6+'Ops_CFADS'!J7+'Ops_CFADS'!J8+'Ops_CFADS'!J9 | K4: ='Ops_CFADS'!K5+'Ops_CFADS'!K6+'Ops_CFADS'!K7+'Ops_CFADS'!K8+'Ops_CFADS'!K9 | ... CM4: ='Ops_CFADS'!CM5+'Ops_CFADS'!CM6+'Ops_CFADS'!CM7+'Ops_CFADS'!CM8+'Ops_CFADS'!CM9
A5: Total Cost_t | C5: $ | D5: =D3+D4 | E5: =E3+E4 | F5: =F3+F4 | G5: =G3+G4 | H5: =H3+H4 | I5: =I3+I4 | J5: =J3+J4 | K5: =K3+K4 | ... CM5: =CM3+CM4
A6: Discount Factor (WACC) | D6: ='Control'!D12 | E6: ='Control'!E12 | F6: ='Control'!F12 | G6: ='Control'!G12 | H6: ='Control'!H12 | I6: ='Control'!I12 | J6: ='Control'!J12 | K6: ='Control'!K12 | ... CM6: ='Control'!CM12
A7: Discounted Cost_t | C7: $ | D7: =D5*D6 | E7: =E5*E6 | F7: =F5*F6 | G7: =G5*G6 | H7: =H5*H6 | I7: =I5*I6 | J7: =J5*J6 | K7: =K5*K6 | ... CM7: =CM5*CM6
A8: H2 Volume_t | C8: kg | D8: ='Ops_CFADS'!D3 | E8: ='Ops_CFADS'!E3 | F8: ='Ops_CFADS'!F3 | G8: ='Ops_CFADS'!G3 | H8: ='Ops_CFADS'!H3 | I8: ='Ops_CFADS'!I3 | J8: ='Ops_CFADS'!J3 | K8: ='Ops_CFADS'!K3 | ... CM8: ='Ops_CFADS'!CM3
A9: Discounted Volume_t | C9: kg | D9: =D8*D6 | E9: =E8*E6 | F9: =F8*F6 | G9: =G8*G6 | H9: =H8*H6 | I9: =I8*I6 | J9: =J8*J6 | K9: =K8*K6 | ... CM9: =CM8*CM6
B11: Discounted Cost NPV | C11: Discounted Volume NPV
A12: TOTALS | B12: =SUM(D7:CM7) | C12: =SUM(D9:CM9)
A14: LCOH ($/kg) | B14: =LCOH_CostNPV/LCOH_VolumeNPV

Sheet Returns_Sensitivities
A1: RETURNS & SENSITIVITIES
A3: Equity Cash Flow | C3: $ | D3: =-('Capex_Construction'!D5+'Capex_Construction'!D8) | E3: =-('Capex_Construction'!E5+'Capex_Construction'!E8) | F3: =-('Capex_Construction'!F5+'Capex_Construction'!F8) | G3: =-('Capex_Construction'!G5+'Capex_Construction'!G8) | H3: =-('Capex_Construction'!H5+'Capex_Construction'!H8) | I3: =-('Capex_Construction'!I5+'Capex_Construction'!I8) | J3: =-('Capex_Construction'!J5+'Capex_Construction'!J8) | K3: =-('Capex_Construction'!K5+'Capex_Construction'!K8) | L3: ='Financials_3Statement'!L6 | M3: ='Financials_3Statement'!M6 | N3: ='Financials_3Statement'!N6 | O3: ='Financials_3Statement'!O6 | P3: ='Financials_3Statement'!P6 | Q3: ='Financials_3Statement'!Q6 | R3: ='Financials_3Statement'!R6 | S3: ='Financials_3Statement'!S6 | ... CM3: ='Financials_3Statement'!CM6
A6: Equity IRR (quarterly, annualized) | B6: =(1+IRR(D3:CM3))^4-1
A8: Min DSCR (operating period) | B8: =MIN(DSCR_Actual_Row)
A9: Avg DSCR (operating period) | B9: =AVERAGE(DSCR_Actual_Row)
A12: SENSITIVITY GRID (populated by RunSensitivityGrid macro)
A13: Scenario | B13: Capex % | C13: Opex % | D13: WACC bps | E13: Utilization % | F13: LCOH | G13: Equity IRR | H13: Min DSCR
A14: Base | B14: 0 | C14: 0 | D14: 0 | E14: 0
A15: Capex +10% | B15: 0.1 | C15: 0 | D15: 0 | E15: 0
A16: Capex -10% | B16: -0.1 | C16: 0 | D16: 0 | E16: 0
A17: Opex +10% | B17: 0 | C17: 0.1 | D17: 0 | E17: 0
A18: Opex -10% | B18: 0 | C18: -0.1 | D18: 0 | E18: 0
A19: WACC +100bps | B19: 0 | C19: 0 | D19: 100 | E19: 0
A20: WACC -100bps | B20: 0 | C20: 0 | D20: -100 | E20: 0
A21: Utilization +5% | B21: 0 | C21: 0 | D21: 0 | E21: 0.05
A22: Utilization -5% | B22: 0 | C22: 0 | D22: 0 | E22: -0.05

Sheet Dashboard
A1: DASHBOARD
A3: LCOH ($/kg) | B3: =LCOH_USD_per_kg
A4: Equity IRR | B4: =EquityIRR
A5: Min DSCR | B5: ='Returns_Sensitivities'!B8
A6: Avg DSCR | B6: ='Returns_Sensitivities'!B9
A7: Gearing Factor (solved) | B7: =GearingFactor
A8: Ending Balance Residual | B8: =EndingBalanceResidual
A9: Convergence Status | B9: =ConvergenceStatus
A10: Iterations Used | B10: =IterationsUsed
A13: [Button: Run Debt Sizing] -- after importing vba/mod_DebtSizing.bas, assign macro 'RunDebtSizing' to a Form Control button here.
A14: [Button: Run Sensitivity Grid] -- assign macro 'RunSensitivityGrid' from vba/mod_Sensitivity.bas here.
